Metadata-Version: 2.1
Name: kemksp
Version: 0.2.1
Summary: A package to manage your KSP Addons
Home-page: https://github.com/kontiko/Kerbal-Extension-Manager
Author: Kontiko
Author-email: kontiko.fb@gmail.com
License: UNKNOWN
Platform: UNKNOWN
Classifier: Programming Language :: Python :: 3
Classifier: Operating System :: OS Independent
Requires-Python: >=3.6
